{
  "parent":"block/cube_all",
  "textures": {
       "down": "skyresourcesclassic:block/ender_core_side",
         "up": "skyresourcesclassic:block/dark_matter_crystallizer",
      "north": "skyresourcesclassic:block/ender_core_side",
      "south": "skyresourcesclassic:block/ender_core_side",
       "west": "skyresourcesclassic:block/ender_core_side",
       "east": "skyresourcesclassic:block/ender_core_side",
   "particle": "skyresourcesclassic:block/dark_matter_crystallizer"
  },
  "display": {
        "thirdperson": {
            "rotation": [ 10, -45, 170 ],
            "translation": [ 0, 1.5, -2.75 ],
            "scale": [ 0.375, 0.375, 0.375 ]
        }
    }
}